symphony/__init__.py
symphony/errors.py
symphony/addons/__init__.py
symphony/addons/docker_builder.py
symphony/addons/docker_cleaner.py
symphony/addons/local_file_manager.py
symphony/commandline/__init__.py
symphony/commandline/commandline_interface.py
symphony/docker/__init__.py
symphony/docker/builder.py
symphony/docker/cluster.py
symphony/docker/experiment.py
symphony/docker/process.py
symphony/docker/process_group.py
symphony/engine/__init__.py
symphony/engine/address_book.py
symphony/engine/application_config.py
symphony/engine/cluster.py
symphony/kube/__init__.py
symphony/kube/builder.py
symphony/kube/cluster.py
symphony/kube/experiment.py
symphony/kube/machine_dispatcher.py
symphony/kube/process.py
symphony/kube/process_group.py
symphony/ray/__init__.py
symphony/ray/driver.py
symphony/ray/kube_cluster.py
symphony/ray/satellite.py
symphony/ray/symph_envs.py
symphony/spec/__init__.py
symphony/spec/base.py
symphony/spec/experiment.py
symphony/spec/process.py
symphony/spec/process_group.py
symphony/subproc/__init__.py
symphony/subproc/cluster.py
symphony/subproc/experiment.py
symphony/subproc/manager.py
symphony/subproc/process.py
symphony/subproc/process_group.py
symphony/tmux/__init__.py
symphony/tmux/cluster.py
symphony/tmux/common.py
symphony/tmux/experiment.py
symphony/tmux/process.py
symphony/tmux/process_group.py
symphony/utils/__init__.py
symphony/utils/common.py
symphony/utils/runner.py
symphony/utils/serialization.py
symphony/utils/threads.py
symphony-0.10.dist-info/METADATA
symphony-0.10.dist-info/RECORD
symphony-0.10.dist-info/WHEEL
symphony-0.10.dist-info/top_level.txt
