Metadata-Version: 2.1
Name: symphony
Version: 0.10
Summary: a distributed process orchestration platform that supports both laptop and major cloud providers
Home-page: https://github.com/SurrealAI/symphony
Author: Surreal AI team
License: GPLv3
Keywords: Orchestration,Kubernetes,Tmux
Platform: UNKNOWN
Classifier: Development Status :: 5 - Production/Stable
Classifier: Topic :: Scientific/Engineering :: Artificial Intelligence
Classifier: Environment :: Console
Classifier: Programming Language :: Python :: 3
Requires-Python: >=3.5
Requires-Dist: libtmux
Requires-Dist: nanolog
Requires-Dist: docker
Requires-Dist: pyyaml
Requires-Dist: benedict (>=0.3)
Requires-Dist: nanolog
